scriptfoundry/__init__.py
scriptfoundry/cli.py
scriptfoundry/constants.py
scriptfoundry/commands/__init__.py
scriptfoundry/commands/new_command.py
scriptfoundry/commands/pack_command.py
scriptfoundry/commands/update_command.py
scriptfoundry/utilities/__init__.py
scriptfoundry/utilities/api_generator.py
scriptfoundry/utilities/check_connectivity.py
scriptfoundry/utilities/config_handler.py
scriptfoundry/utilities/template_handler.py
scriptfoundry/utilities/zip_archive_handler.py
cloudshell_scriptfoundry-0.1.2.dist-info/LICENSE
cloudshell_scriptfoundry-0.1.2.dist-info/METADATA
cloudshell_scriptfoundry-0.1.2.dist-info/WHEEL
cloudshell_scriptfoundry-0.1.2.dist-info/entry_points.txt
cloudshell_scriptfoundry-0.1.2.dist-info/top_level.txt
cloudshell_scriptfoundry-0.1.2.dist-info/RECORD
