Metadata-Version: 2.1
Name: cloudshell-scriptfoundry
Version: 0.1.2
Summary: A CLI way to generate and upload cloudshell orchestration scripts
Home-page: https://github.com/QualiSystemsLab/cloudshell-scriptfoundry
Author: QualiLab
Author-email: support@qualisystems.com
License: MIT
Classifier: Programming Language :: Python :: 3.9
Classifier: License :: OSI Approved :: MIT License
Classifier: Operating System :: OS Independent
Requires-Python: >=3.9
License-File: LICENSE
Requires-Dist: shellfoundry
Requires-Dist: cloudshell-automation-api
